{"command.restartServer":"サーバーの再起動","extension.description":"flake8 の使用による Python ファイルのリンティングのサポート。","settings.args.description":"渡された引数。各引数は、配列内の個別の文字列です。","settings.cwd.description":"'flake8' の実行に使用される現在の作業ディレクトリ。現在リントされているファイルのディレクトリを使用するには、'${fileDirname}' を使用できます。","settings.ignorePatterns.description":"ファイルまたはフォルダーをリントから除外するために使用されるパターン。","settings.importStrategy.description":"`flake8` のインポート元を定義します。`flake8.path` が設定されている場合、この設定は無視される可能性があります。","settings.importStrategy.fromEnvironment.description":"環境から `flake8` を使用します。`flake8` が環境で使用できない場合にのみ、バンドルされたバージョンにフォールバックします。","settings.importStrategy.useBundled.description":"バンドルされたバージョンの `flake8` を常に使用してください。","settings.interpreter.description":"Python 実行可能ファイルへのパスに設定すると、拡張機能ではそれを使用してサーバーとサブプロセスを起動します。","settings.path.description":"`flake8` バイナリへのパスに設定すると、拡張機能ではそれをリンティングに使用します。注: このオプションを使用すると、リンティングが遅くなる可能性があります。","settings.severity.description":"`flake8` メッセージ タイプの重大度から、問題ウィンドウに表示される重大度へのマッピング。","settings.showNotifications.always.description":"サーバーが表示するように選択したすべてのものについて、通知が表示されます。","settings.showNotifications.description":"この拡張機能によって通知が表示されるタイミングを制御します。","settings.showNotifications.off.description":"すべての通知がオフになっています。エラーや警告はログで引き続き利用できます。","settings.showNotifications.onError.description":"通知はエラーの場合にのみ表示されます。","settings.showNotifications.onWarning.description":"エラーと警告の通知が表示されます。"}
